Workbook

Sheet Read Me
A1: Pre-Construction Document Delivery Register
A2: Project | B2: PROJ
A3: What this is | B3: Controlled index of all 74 pre-construction design and information deliverables, in the same structure and house style as the Pre-Construction Commercial Register so the two form one document-control pack.
A4: Spine | B4: Divided into three procurement gates matching the commercial register: Stage 1 - Bid & Tender, Stage 2 - Contract Award, Stage 3 - Pre-Construction. The earlier A-E lifecycle sections have been removed.
A5: Stage 1 - Bid & Tender | B5: Documents submitted or required as part of the tender/bid to secure the project. NOTE: this stage spans both Meridian's own tender submissions and the client-issued tender information the bid is priced against (much of it Client-owned). Filter on the Owner column if you need only Meridian submissions.
A6: Stage 2 - Contract Award | B6: Documents submitted once the contract is awarded and Meridian is appointed to undertake the PCSA — the pre-con execution and delivery-control set (PEP, RACI, WBS, design programme, procurement/long-lead, technical-submission schedule). Deliberately lean: at appointment you issue how you'll run pre-con, not the design itself.
A7: Stage 3 - Pre-Construction | B7: Documents delivered on completion of pre-con — coordinated design, IFC technical packages, building-control compliance, procurement/work packages, final contract documents, commissioning and readiness.
A8: Sheets | B8: Read Me / Stage 1-3 checklists (views) / Design Folder Structure / Master Register (single source of truth, all 74) / Folder Coverage / Dashboard (live counts) / Guidance & Lookups.
A9: Naming (proposed) | B9: PROJ-DDR-[TYPE]-[####]_[Title]. DDR = Design Delivery Register; each L2 folder has a unique TYPE. Proposed convention — confirm before issuing. Meridian-commercial (MCR-CM) codes are deliberately NOT used, as most items are Client/design-team owned.
A10: Input fields | B10: Include in Pack?, Status, Priority, Due Date, Contributors, Storage Link and Notes are controlled input fields (dropdowns where relevant) — blank/defaulted, to be completed live. Not pre-populated with assumed values.
A11: Judgment calls | B11: Stage assignment on boundary items is a call, not a fact. Watch: 3.02 planning-conditions tracker (S1 as baseline vs S3 discharge), 3.14/3.18/3.19 final ER & design-responsibility (placed S3 as contract-completion docs), 4.03 technical-submission schedule (S2 as a control). Move any of these in the Master Register and every view/count updates. Ref numbers (0.01-4.21) are the design team's own — preserved, do not overwrite.

Sheet Stage 1 - Bid & Tender
A1: Stage 1 - Bid & Tender
A2: =COUNTIF('Master Register'!$B$4:$B$76,$A$1)&" deliverables · Rev P01" -> 20 deliverables · Rev P01
A3: Documents submitted or required as part of the tender/bid process to secure the project. Spans both Meridian's tender submissions AND the client-issued tender information the bid is priced against. Filtered view of the Master Register — edit items there, not here.
A5: Ref | B5: Pre-Construction Document / Deliverable | C5: Purpose / Assurance Provided | D5: Owner / Lead Party | E5: Folder (L2) | F5: TYPE | G5: Proposed File Name
A6: 0.01 | B6: Development Business Case and Development Appraisal | C6: Confirms the commercial case, development value and delivery assumptions. | D6: Client | E6: 1.10 Development & Investment Basis | F6: DEV | G6: PROJ-DDR-DEV-0001_DevelopmentBusinessCaseAndDe
A7: 0.02 | B7: Client Strategic Brief | C7: Defines Client's required project outcomes and success criteria. | D7: Client | E7: 1.10 Development & Investment Basis | F7: DEV | G7: PROJ-DDR-DEV-0002_ClientStrategicBrief
A8: 0.03 | B8: Site Acquisition and Due Diligence Summary | C8: Consolidates material site, title and development constraints. | D8: Client | E8: 1.10 Development & Investment Basis | F8: DEV | G8: PROJ-DDR-DEV-0003_SiteAcquisitionAndDueDiligen
A9: 0.04 | B9: Feasibility and Development Options Appraisal | C9: Records the options considered and why the approved development solution was selected. | D9: Client | E9: 1.10 Development & Investment Basis | F9: DEV | G9: PROJ-DDR-DEV-0004_FeasibilityAndDevelopmentOpt
A10: 0.05 | B10: Planning and Development Capacity Appraisal | C10: Records the planning policy and capacity basis preceding the approved permission. | D10: Client | E10: 1.10 Development & Investment Basis | F10: DEV | G10: PROJ-DDR-DEV-0005_PlanningAndDevelopmentCapaci
A11: 0.06 | B11: Initial Development Programme | C11: Sets the overall development, approvals, procurement and construction milestones. | D11: Client | E11: 1.10 Development & Investment Basis | F11: DEV | G11: PROJ-DDR-DEV-0007_InitialDevelopmentProgramme
A12: 0.07 | B12: Development Risk, Abnormals and Procurement Strategy | C12: Combines the principal development risks with the intended procurement and contract route. | D12: Client | E12: 1.10 Development & Investment Basis | F12: DEV | G12: PROJ-DDR-DEV-0008_DevelopmentRiskAbnormalsAndP
A13: 1.01 | B13: Developed Project Brief | C13: Translates Client's objectives into coordinated, measurable project requirements. | D13: Client | E13: 1.20 Project Brief & Scope | F13: BRF | G13: PROJ-DDR-BRF-0001_DevelopedProjectBrief
A14: 1.02 | B14: Development Specification and Quality Brief | C14: Defines the intended development-wide quality and performance standard. | D14: Client | E14: 1.20 Project Brief & Scope | F14: BRF | G14: PROJ-DDR-BRF-0002_DevelopmentSpecificationAndQ
A15: 1.03 | B15: Accommodation, Apartment Type and Area Schedule | C15: Controls the approved unit mix and project area data. | D15: Client | E15: 1.20 Project Brief & Scope | F15: BRF | G15: PROJ-DDR-BRF-0003_AccommodationApartmentTypeAn
A16: 1.09 | B16: Survey Requirements and Existing Information Register | C16: Records required surveys and the status/reliability of existing information. | D16: Client | E16: 1.30 Surveys, Planning & Statutory Baseline | F16: PSB | G16: PROJ-DDR-PSB-0001_SurveyRequirementsAndExistin
A17: 1.10 | B17: Planning and Statutory Approval Information Register | C17: Creates the controlled index of the approved planning and statutory information. | D17: Client | E17: 1.30 Surveys, Planning & Statutory Baseline | F17: PSB | G17: PROJ-DDR-PSB-0002_PlanningAndStatutoryApproval
A18: 1.11 | B18: Building Control Route and Transitional Regulations Record | C18: Records why the project proceeds under the confirmed previous/transitional regulations route. | D18: Client | E18: 1.30 Surveys, Planning & Statutory Baseline | F18: PSB | G18: PROJ-DDR-PSB-0003_BuildingControlRouteAndTrans
A19: 1.12 | B19: Utilities, Sustainability, Energy and EPC Brief | C19: Defines utility capacity, infrastructure and performance requirements. | D19: Client | E19: 1.40 Utilities & Sustainability Brief | F19: UTB | G19: PROJ-DDR-UTB-0001_UtilitiesSustainabilityEnerg
A20: 1.13 | B20: Pre-Construction Information and CDM Design Risk Register | C20: Provides existing safety information and records significant design risks. | D20: Client / CDM Principal Designer | E20: 1.30 Surveys, Planning & Statutory Baseline | F20: PSB | G20: PROJ-DDR-PSB-0004_PreConstructionInformationAn
A21: 1.14 | B21: Outline Employer's Requirements | C21: Establishes the structure and content of Client's contractual requirements. | D21: Client | E21: 1.20 Project Brief & Scope | F21: BRF | G21: PROJ-DDR-BRF-0004_OutlineEmployerSRequirements
A22: 2.02 | B22: Planning Application and Supporting Documents Register | C22: Indexes the historic application that achieved planning permission. | D22: Client | E22: 1.30 Surveys, Planning & Statutory Baseline | F22: PSB | G22: PROJ-DDR-PSB-0005_PlanningApplicationAndSuppor
A23: 2.05 | B23: MEP Concept and Heating, Cooling and Ventilation Options Appraisal | C23: Defines the building-services strategy and records the system-selection decision. | D23: Client | E23: 1.50 Concept Design & Performance | F23: CPT | G23: PROJ-DDR-CPT-0004_MEPConceptAndHeatingCoolingA
A24: 3.01 | B24: Planning Decision Notice and Approved Drawing/Document Register | C24: Establishes the definitive planning-approved baseline. | D24: Client | E24: 1.30 Surveys, Planning & Statutory Baseline | F24: PSB | G24: PROJ-DDR-PSB-0006_PlanningDecisionNoticeAndApp
A25: 3.02 | B25: Planning Conditions, Section 106 and CIL Tracker | C25: Controls every planning condition and obligation by trigger date. | D25: Client | E25: 1.30 Surveys, Planning & Statutory Baseline | F25: PSB | G25: PROJ-DDR-PSB-0007_PlanningConditionsSection106

Sheet Stage 2 - Contract Award
A1: Stage 2 - Contract Award
A2: =COUNTIF('Master Register'!$B$4:$B$76,$A$1)&" deliverables · Rev P01" -> 19 deliverables · Rev P01
A3: Documents submitted once the contract is awarded and Meridian is appointed to undertake the PCSA — the pre-construction execution and delivery-control set. Filtered view of the Master Register — edit items there, not here.
A5: Ref | B5: Pre-Construction Document / Deliverable | C5: Purpose / Assurance Provided | D5: Owner / Lead Party | E5: Folder (L2) | F5: TYPE | G5: Proposed File Name
A6: 1.04 | B6: Project Execution Plan, Organisation and Appointment Schedule | C6: Defines project governance, reporting, appointments and decision routes. | D6: Client initially / Meridian post-appointment | E6: 2.10 Pre-Con Execution & Governance | F6: PEG | G6: PROJ-DDR-PEG-0001_ProjectExecutionPlanOrganisa
A7: 1.05 | B7: Design Responsibility Matrix and RACI | C7: Allocates design, coordination, review and acceptance responsibility. | D7: Client initially / Meridian post-appointment | E7: 2.10 Pre-Con Execution & Governance | F7: PEG | G7: PROJ-DDR-PEG-0002_DesignResponsibilityMatrixAn
A8: 1.06 | B8: Work Breakdown Structure and Scope Breakdown | C8: Structures the project by system, trade, package and deliverable. | D8: Client initially / Meridian post-appointment | E8: 2.10 Pre-Con Execution & Governance | F8: PEG | G8: PROJ-DDR-PEG-0003_WorkBreakdownStructureAndSco
A9: 1.07 | B9: Design Programme and Information Release Schedule | C9: Baselines design deliverables and approval periods against project need-by dates. | D9: Meridian | E9: 2.20 Design Programme & Procurement | F9: DPP | G9: PROJ-DDR-DPP-0001_DesignProgrammeAndInformatio
A10: 1.08 | B10: Design Procurement and Long-Lead Schedule | C10: Links appointments and procurement to required design outputs. | D10: Meridian | E10: 2.20 Design Programme & Procurement | F10: DPP | G10: PROJ-DDR-DPP-0002_DesignProcurementAndLongLead
A11: 2.01 | B11: Concept Design Report and Concept Drawing Set | C11: Records the coordinated concept response to the Project Brief. | D11: Client | E11: 1.50 Concept Design & Performance | F11: CPT | G11: PROJ-DDR-CPT-0001_ConceptDesignReportAndConcep
A12: 2.03 | B12: Updated Accommodation and Development Area Schedule | C12: Confirms the concept-stage unit and area data. | D12: Client | E12: 1.50 Concept Design & Performance | F12: CPT | G12: PROJ-DDR-CPT-0002_UpdatedAccommodationAndDevel
A13: 2.04 | B13: Structural, Civil and Drainage Concept Strategy | C13: Defines the structural form, foundations, drainage and civil engineering basis. | D13: Client | E13: 1.50 Concept Design & Performance | F13: CPT | G13: PROJ-DDR-CPT-0003_StructuralCivilAndDrainageCo
A14: 2.06 | B14: Outline Fire and Life-Safety Strategy | C14: Defines the concept fire-safety basis for the non-HRB residential building. | D14: Client | E14: 1.50 Concept Design & Performance | F14: CPT | G14: PROJ-DDR-CPT-0005_OutlineFireAndLifeSafetyStra
A15: 2.07 | B15: Energy, SAP, EPC, Overheating and Acoustic Performance Strategy | C15: Combines key performance studies that influence the fabric and MEP design. | D15: Client | E15: 1.50 Concept Design & Performance | F15: CPT | G15: PROJ-DDR-CPT-0006_EnergySAPEPCOverheatingAndAc
A16: 2.08 | B16: Access, External Works, Landscape, Parking, Refuse and Security Strategy | C16: Coordinates the main site and inclusive-access requirements. | D16: Client | E16: 1.50 Concept Design & Performance | F16: CPT | G16: PROJ-DDR-CPT-0007_AccessExternalWorksLandscape
... A24: 4.03 | B24: Master Design Delivery and Technical Submission Schedule | C24: Controls all Technical Design , Design review and approval dates. | D24: Meridian | E24: 2.20 Design Programme & Procurement | F24: DPP | G24: PROJ-DDR-DPP-0003_MasterDesignDeliveryAndTechn

Sheet Stage 3 - Pre-Construction
A1: Stage 3 - Pre-Construction
A2: =COUNTIF('Master Register'!$B$4:$B$76,$A$1)&" deliverables · Rev P01" -> 34 deliverables · Rev P01
A3: Documents delivered on completion of the pre-construction phase — the coordinated and technical information that readies the works for construction, including the final contract documents. Filtered view of the Master Register — edit items there, not here.
A5: Ref | B5: Pre-Construction Document / Deliverable | C5: Purpose / Assurance Provided | D5: Owner / Lead Party | E5: Folder (L2) | F5: TYPE | G5: Proposed File Name
A6: 3.03 | B6: Spatial Coordination Report | C6: Records the coordinated design status and unresolved interfaces. | D6: Meridian | E6: 3.10 Coordinated Design Packages | F6: CRD | G6: PROJ-DDR-CRD-0001_SpatialCoordinationReport
A7: 3.04 | B7: Coordinated Architectural Design Package | C7: Provides the controlled spatial and planning-compliant architectural design. | D7: Meridian | E7: 3.10 Coordinated Design Packages | F7: CRD | G7: PROJ-DDR-CRD-0002_CoordinatedArchitecturalDesi
A8: 3.05 | B8: Coordinated Structural, Civil, Drainage and Levels Package | C8: Coordinates primary engineering, drainage and external levels. | D8: Relevant engineers | E8: 3.10 Coordinated Design Packages | F8: CRD | G8: PROJ-DDR-CRD-0003_CoordinatedStructuralCivilDr
A9: 3.06 | B9: Coordinated MEP and Final Heating/Ventilation Strategy | C9: Coordinates services in space and freezes the principal systems. | D9: MEP Designer | E9: 3.10 Coordinated Design Packages | F9: CRD | G9: PROJ-DDR-CRD-0004_CoordinatedMEPAndFinalHeatin
A10: 3.07 | B10: Developed Fire, Compartmentation and Building Regulations Compliance Package | C10: Coordinates the fire and Building Regulations design basis. | D10: Relevant designers | E10: 3.10 Coordinated Design Packages | F10: CRD | G10: PROJ-DDR-CRD-0005_DevelopedFireCompartmentatio
A11: 3.08 | B11: SOCOTEC Submission, Comments and Actions Register | C11: Controls Building Control information and responses. | D11: Client / Meridian | E11: 3.30 Building Control & Compliance | F11: BCC | G11: PROJ-DDR-BCC-0001_SOCOTECSubmissionCommentsAnd
A12: 3.09 | B12: Apartment Type, Area, Sales and Purchaser Information Pack | C12: Maintains one controlled residential product and sales basis. | D12: Client | E12: 3.20 Detailed Specs, Product & Sales | F12: SPC | G12: PROJ-DDR-SPC-0001_ApartmentTypeAreaSalesAndPur
A13: 3.10 | B13: External Works, Landscape, Parking, Refuse and Access Package | C13: Coordinates the approved site design and interfaces. | D13: Client | E13: 3.10 Coordinated Design Packages | F13: CRD | G13: PROJ-DDR-CRD-0006_ExternalWorksLandscapeParkin
A14: 3.11 | B14: Utilities, EV, PV and Incoming Services Coordination Pack | C14: Coordinates connection requirements with the building and site design. | D14: Client / Meridian | E14: 3.10 Coordinated Design Packages | F14: CRD | G14: PROJ-DDR-CRD-0007_UtilitiesEVPVAndIncomingServ
A15: 3.12 | B15: BIM, Clash Detection and Interface Resolution Report | C15: Defines model responsibilities and records coordination outcomes where BIM is used. | D15: Meridian | E15: 3.10 Coordinated Design Packages | F15: CRD | G15: PROJ-DDR-CRD-0008_BIMClashDetectionAndInterfac
A16: 3.13 | B16: Detailed Specifications, Finishes and Room Data Schedules | C16: Defines the coordinated quality, performance and room requirements. | D16: Client | E16: 3.20 Detailed Specs, Product & Sales | F16: SPC | G16: PROJ-DDR-SPC-0002_DetailedSpecificationsFinish
... A39: 4.21 | B39: Technical Design Readiness Report | C39: Records whether each package is ready for procurement and construction. | D39: Meridian | E39: 3.80 Commissioning & Readiness | F39: CMR | G39: PROJ-DDR-CMR-0002_TechnicalDesignReadinessRepo

Sheet Design Folder Structure
A1: Design Delivery — Folder Structure (Proposed)
A2: L1 = procurement stage; L2 = deliverable grouping. Aligned to the 3-stage spine for simplicity. Confirm before adopting.
A4: L1 Code | B4: Level 1 Folder (Stage) | C4: L2 Code | D4: Level 2 Folder | E4: TYPE | F4: Lead Owner | G4: Items
A5: 1.0 | B5: Stage 1 - Bid & Tender
C6: 1.10 | D6: Development & Investment Basis | E6: DEV | F6: Client | G6: 8
C7: 1.20 | D7: Project Brief & Scope | E7: BRF | F7: Client | G7: 4
C8: 1.30 | D8: Surveys, Planning & Statutory Baseline | E8: PSB | F8: Client | G8: 7
C9: 1.40 | D9: Utilities & Sustainability Brief | E9: UTB | F9: Client | G9: 1
C10: 1.50 | D10: Concept Design & Performance | E10: CPT | F10: Client | G10: 11
C11: 1.60 | D11: Tender Scope & Contractor's Proposals | E11: TEN | F11: Meridian | G11: 3
A12: 2.0 | B12: Stage 2 - Contract Award
C13: 2.10 | D13: Pre-Con Execution & Governance | E13: PEG | F13: Client initially | G13: 3
C14: 2.20 | D14: Design Programme & Procurement | E14: DPP | F14: Meridian | G14: 3
A15: 3.0 | B15: Stage 3 - Pre-Construction
C16: 3.10 | D16: Coordinated Design Packages | E16: CRD | F16: Meridian | G16: 8
C17: 3.20 | D17: Detailed Specs, Product & Sales | E17: SPC | F17: Client | G17: 2
C18: 3.30 | D18: Building Control & Compliance | E18: BCC | F18: Client | G18: 3
C19: 3.40 | D19: Final Contract Documents | E19: FCD | F19: Meridian | G19: 5
C20: 3.50 | D20: IFC Technical Packages | E20: IFC | F20: Meridian | G20: 7
C21: 3.60 | D21: Procurement & Specialist Design | E21: PSD | F21: Meridian | G21: 4
C22: 3.70 | D22: Planning Discharge, Risk & Change | E22: PRC | F22: Client | G22: 3
C23: 3.80 | D23: Commissioning & Readiness | E23: CMR | F23: Meridian | G23: 2

Sheet Master Register
A1: PROJ Canalside Regency — Pre-Construction Delivery Master Register
A3: Ref | B3: Stage | C3: Pre-Construction Document / Deliverable | D3: Purpose / Assurance Provided | E3: Include in Pack? | F3: Status | G3: Priority | H3: Owner / Lead Party | I3: Contributors | J3: Audience | K3: Due Date | L3: Current Version | M3: Storage Link / File Ref | N3: Source / Basis | O3: Notes / Action | P3: Level 1 Folder | Q3: Level 2 Folder | R3: TYPE | S3: Proposed File Name
A4: 0.01 | B4: Stage 1 - Bid & Tender | C4: Development Business Case and Development Appraisal | D4: Confirms the commercial case, development value and delivery assumptions. | E4: TBC | F4: Not Started | H4: Client | L4: Rev P01 | N4: Design Delivery Register Rev P01 | P4: Stage 1 - Bid & Tender | Q4: 1.10 Development & Investment Basis | R4: DEV | S4: PROJ-DDR-DEV-0001_DevelopmentBusinessCaseAndDe
A5: 0.02 | B5: Stage 1 - Bid & Tender | C5: Client Strategic Brief | D5: Defines Client's required project outcomes and success criteria. | E5: TBC | F5: Not Started | H5: Client | L5: Rev P01 | N5: Design Delivery Register Rev P01 | P5: Stage 1 - Bid & Tender | Q5: 1.10 Development & Investment Basis | R5: DEV | S5: PROJ-DDR-DEV-0002_ClientStrategicBrief
A6: 0.03 | B6: Stage 1 - Bid & Tender | C6: Site Acquisition and Due Diligence Summary | D6: Consolidates material site, title and development constraints. | E6: TBC | F6: Not Started | H6: Client | L6: Rev P01 | N6: Design Delivery Register Rev P01 | P6: Stage 1 - Bid & Tender | Q6: 1.10 Development & Investment Basis | R6: DEV | S6: PROJ-DDR-DEV-0003_SiteAcquisitionAndDueDiligen
A7: 0.04 | B7: Stage 1 - Bid & Tender | C7: Feasibility and Development Options Appraisal | D7: Records the options considered and why the approved development solution was selected. | E7: TBC | F7: Not Started | H7: Client | L7: Rev P01 | N7: Design Delivery Register Rev P01 | P7: Stage 1 - Bid & Tender | Q7: 1.10 Development & Investment Basis | R7: DEV | S7: PROJ-DDR-DEV-0004_FeasibilityAndDevelopmentOpt
A8: 0.05 | B8: Stage 1 - Bid & Tender | C8: Planning and Development Capacity Appraisal | D8: Records the planning policy and capacity basis preceding the approved permission. | E8: TBC | F8: Not Started | H8: Client | L8: Rev P01 | N8: Design Delivery Register Rev P01 | P8: Stage 1 - Bid & Tender | Q8: 1.10 Development & Investment Basis | R8: DEV | S8: PROJ-DDR-DEV-0005_PlanningAndDevelopmentCapaci
A9: 0.06 | B9: Stage 1 - Bid & Tender | C9: Initial Development Programme | D9: Sets the overall development, approvals, procurement and construction milestones. | E9: TBC | F9: Not Started | H9: Client | L9: Rev P01 | N9: Design Delivery Register Rev P01 | P9: Stage 1 - Bid & Tender | Q9: 1.10 Development & Investment Basis | R9: DEV | S9: PROJ-DDR-DEV-0007_InitialDevelopmentProgramme
A10: 0.07 | B10: Stage 1 - Bid & Tender | C10: Development Risk, Abnormals and Procurement Strategy | D10: Combines the principal development risks with the intended procurement and contract route. | E10: TBC | F10: Not Started | H10: Client | L10: Rev P01 | N10: Design Delivery Register Rev P01 | P10: Stage 1 - Bid & Tender | Q10: 1.10 Development & Investment Basis | R10: DEV | S10: PROJ-DDR-DEV-0008_DevelopmentRiskAbnormalsAndP
A11: 1.01 | B11: Stage 1 - Bid & Tender | C11: Developed Project Brief | D11: Translates Client's objectives into coordinated, measurable project requirements. | E11: TBC | F11: Not Started | H11: Client | L11: Rev P01 | N11: Design Delivery Register Rev P01 | P11: Stage 1 - Bid & Tender | Q11: 1.20 Project Brief & Scope | R11: BRF | S11: PROJ-DDR-BRF-0001_DevelopedProjectBrief
A12: 1.02 | B12: Stage 1 - Bid & Tender | C12: Development Specification and Quality Brief | D12: Defines the intended development-wide quality and performance standard. | E12: TBC | F12: Not Started | H12: Client | L12: Rev P01 | N12: Design Delivery Register Rev P01 | P12: Stage 1 - Bid & Tender | Q12: 1.20 Project Brief & Scope | R12: BRF | S12: PROJ-DDR-BRF-0002_DevelopmentSpecificationAndQ
A13: 1.03 | B13: Stage 1 - Bid & Tender | C13: Accommodation, Apartment Type and Area Schedule | D13: Controls the approved unit mix and project area data. | E13: TBC | F13: Not Started | H13: Client | L13: Rev P01 | N13: Design Delivery Register Rev P01 | P13: Stage 1 - Bid & Tender | Q13: 1.20 Project Brief & Scope | R13: BRF | S13: PROJ-DDR-BRF-0003_AccommodationApartmentTypeAn
A14: 1.09 | B14: Stage 1 - Bid & Tender | C14: Survey Requirements and Existing Information Register | D14: Records required surveys and the status/reliability of existing information. | E14: TBC | F14: Not Started | H14: Client | L14: Rev P01 | N14: Design Delivery Register Rev P01 | P14: Stage 1 - Bid & Tender | Q14: 1.30 Surveys, Planning & Statutory Baseline | R14: PSB | S14: PROJ-DDR-PSB-0001_SurveyRequirementsAndExistin
A15: 1.10 | B15: Stage 1 - Bid & Tender | C15: Planning and Statutory Approval Information Register | D15: Creates the controlled index of the approved planning and statutory information. | E15: TBC | F15: Not Started | H15: Client | L15: Rev P01 | N15: Design Delivery Register Rev P01 | P15: Stage 1 - Bid & Tender | Q15: 1.30 Surveys, Planning & Statutory Baseline | R15: PSB | S15: PROJ-DDR-PSB-0002_PlanningAndStatutoryApproval
A16: 1.11 | B16: Stage 1 - Bid & Tender | C16: Building Control Route and Transitional Regulations Record | D16: Records why the project proceeds under the confirmed previous/transitional regulations route. | E16: TBC | F16: Not Started | H16: Client | L16: Rev P01 | N16: Design Delivery Register Rev P01 | P16: Stage 1 - Bid & Tender | Q16: 1.30 Surveys, Planning & Statutory Baseline | R16: PSB | S16: PROJ-DDR-PSB-0003_BuildingControlRouteAndTrans
A17: 1.12 | B17: Stage 1 - Bid & Tender | C17: Utilities, Sustainability, Energy and EPC Brief | D17: Defines utility capacity, infrastructure and performance requirements. | E17: TBC | F17: Not Started | H17: Client | L17: Rev P01 | N17: Design Delivery Register Rev P01 | P17: Stage 1 - Bid & Tender | Q17: 1.40 Utilities & Sustainability Brief | R17: UTB | S17: PROJ-DDR-UTB-0001_UtilitiesSustainabilityEnerg
A18: 1.13 | B18: Stage 1 - Bid & Tender | C18: Pre-Construction Information and CDM Design Risk Register | D18: Provides existing safety information and records significant design risks. | E18: TBC | F18: Not Started | H18: Client / CDM Principal Designer | L18: Rev P01 | N18: Design Delivery Register Rev P01 | P18: Stage 1 - Bid & Tender | Q18: 1.30 Surveys, Planning & Statutory Baseline | R18: PSB | S18: PROJ-DDR-PSB-0004_PreConstructionInformationAn
A19: 1.14 | B19: Stage 1 - Bid & Tender | C19: Outline Employer's Requirements | D19: Establishes the structure and content of Client's contractual requirements. | E19: TBC | F19: Not Started | H19: Client | L19: Rev P01 | N19: Design Delivery Register Rev P01 | P19: Stage 1 - Bid & Tender | Q19: 1.20 Project Brief & Scope | R19: BRF | S19: PROJ-DDR-BRF-0004_OutlineEmployerSRequirements
A20: 2.02 | B20: Stage 1 - Bid & Tender | C20: Planning Application and Supporting Documents Register | D20: Indexes the historic application that achieved planning permission. | E20: TBC | F20: Not Started | H20: Client | L20: Rev P01 | N20: Design Delivery Register Rev P01 | P20: Stage 1 - Bid & Tender | Q20: 1.30 Surveys, Planning & Statutory Baseline | R20: PSB | S20: PROJ-DDR-PSB-0005_PlanningApplicationAndSuppor
A21: 2.05 | B21: Stage 1 - Bid & Tender | C21: MEP Concept and Heating, Cooling and Ventilation Options Appraisal | D21: Defines the building-services strategy and records the system-selection decision. | E21: TBC | F21: Not Started | H21: Client | L21: Rev P01 | N21: Design Delivery Register Rev P01 | P21: Stage 1 - Bid & Tender | Q21: 1.50 Concept Design & Performance | R21: CPT | S21: PROJ-DDR-CPT-0004_MEPConceptAndHeatingCoolingA
A22: 3.01 | B22: Stage 1 - Bid & Tender | C22: Planning Decision Notice and Approved Drawing/Document Register | D22: Establishes the definitive planning-approved baseline. | E22: TBC | F22: Not Started | H22: Client | L22: Rev P01 | N22: Design Delivery Register Rev P01 | P22: Stage 1 - Bid & Tender | Q22: 1.30 Surveys, Planning & Statutory Baseline | R22: PSB | S22: PROJ-DDR-PSB-0006_PlanningDecisionNoticeAndApp
... A76: 4.21 | B76: Stage 3 - Pre-Construction | C76: Technical Design Readiness Report | D76: Records whether each package is ready for procurement and construction. | E76: TBC | F76: Not Started | H76: Meridian | L76: Rev P01 | N76: Design Delivery Register Rev P01 | P76: Stage 3 - Pre-Construction | Q76: 3.80 Commissioning & Readiness | R76: CMR | S76: PROJ-DDR-CMR-0002_TechnicalDesignReadinessRepo

Sheet Folder Coverage
A1: Folder Coverage — items per stage
A3: L1 Code | B3: Level 1 Folder (Stage) | C3: Items
A4: 1.0 | B4: Stage 1 - Bid & Tender | C4: =COUNTIF('Master Register'!$B$4:$B$76,B4) -> 20
A5: 2.0 | B5: Stage 2 - Contract Award | C5: =COUNTIF('Master Register'!$B$4:$B$76,B5) -> 19
A6: 3.0 | B6: Stage 3 - Pre-Construction | C6: =COUNTIF('Master Register'!$B$4:$B$76,B6) -> 34
B7: TOTAL | C7: =SUM(C4:C6) -> 73

Sheet Dashboard
A1: PROJ Pre-Construction Delivery — Dashboard
A2: Live counts off the Master Register. Set Include / Status / Priority / Due Date there and these update.
A4: Control | B4: Count | D4: Progress | E4: Result
A5: Total deliverables | B5: =COUNTA('Master Register'!$A$4:$A$76) -> 73 | D5: Applicability reviewed | E5: =IF(B5=0,0,(B6+B7)/B5) -> 0
A6: Included - Yes | B6: =COUNTIF('Master Register'!$E$4:$E$76,"Yes") -> 0 | D6: Completed | E6: =COUNTIF('Master Register'!$F$4:$F$76,"Complete") -> 0
A7: Excluded - No | B7: =COUNTIF('Master Register'!$E$4:$E$76,"No") -> 0 | D7: In progress | E7: =COUNTIF('Master Register'!$F$4:$F$76,"In Progress") -> 0
A8: Still TBC | B8: =COUNTIF('Master Register'!$E$4:$E$76,"TBC") -> 73 | D8: Not started | E8: =COUNTIF('Master Register'!$F$4:$F$76,"Not Started") -> 73
A9: Critical priority | B9: =COUNTIF('Master Register'!$G$4:$G$76,"Critical") -> 0 | D9: Overdue open | E9: =COUNTIFS('Master Register'!$K$4:$K$76,"<"&TODAY(),'Master Register'!$K$4:$K$76,"<>",'Master Register'!$F$4:$F$76,"<>Complete") -> 0
A11: Deliverables by owner / lead party | G11: Deliverables by stage
A12: Owner / Lead Party | B12: Documents | G12: Stage | H12: Documents
A13: CDM Principal Designer / Meridian | B13: =COUNTIF('Master Register'!$H$4:$H$76,A13) -> 1 | G13: Stage 1 - Bid & Tender | H13: =COUNTIF('Master Register'!$B$4:$B$76,G13) -> 20
A14: Client | B14: =COUNTIF('Master Register'!$H$4:$H$76,A14) -> 35 | G14: Stage 2 - Contract Award | H14: =COUNTIF('Master Register'!$B$4:$B$76,G14) -> 19
A15: Client / CDM Principal Designer | B15: =COUNTIF('Master Register'!$H$4:$H$76,A15) -> 1 | G15: Stage 3 - Pre-Construction | H15: =COUNTIF('Master Register'!$B$4:$B$76,G15) -> 34
A16: Client / Meridian | B16: =COUNTIF('Master Register'!$H$4:$H$76,A16) -> 4 | G16: TOTAL | H16: =SUM(H13:H15) -> 73
A17: Client / design team | B17: =COUNTIF('Master Register'!$H$4:$H$76,A17) -> 1
A18: Client initially / Meridian post-appointment | B18: =COUNTIF('Master Register'!$H$4:$H$76,A18) -> 3
A19: MEP / specialist designers | B19: =COUNTIF('Master Register'!$H$4:$H$76,A19) -> 1
A20: MEP Designer | B20: =COUNTIF('Master Register'!$H$4:$H$76,A20) -> 1
A21: Meridian | B21: =COUNTIF('Master Register'!$H$4:$H$76,A21) -> 17
A22: Meridian / CDP specialists | B22: =COUNTIF('Master Register'!$H$4:$H$76,A22) -> 1
A23: Meridian / Client | B23: =COUNTIF('Master Register'!$H$4:$H$76,A23) -> 1
A24: Meridian / appointed architectural designer | B24: =COUNTIF('Master Register'!$H$4:$H$76,A24) -> 1
A25: Meridian / relevant designers | B25: =COUNTIF('Master Register'!$H$4:$H$76,A25) -> 1
A26: Relevant designers | B26: =COUNTIF('Master Register'!$H$4:$H$76,A26) -> 2
A27: Relevant designers / CDP specialists | B27: =COUNTIF('Master Register'!$H$4:$H$76,A27) -> 1
A28: Relevant engineers | B28: =COUNTIF('Master Register'!$H$4:$H$76,A28) -> 2

Sheet Guidance & Lookups
A1: How to Use This Register
A3: Field | B3: Required use | C3: Do not do | E3: Owner / Lead Party Lookup | F3: Values
A4: Stage | B4: Set by procurement gate: 1 Bid & Tender / 2 Contract Award / 3 Pre-Construction. | C4: Do not leave a deliverable unstaged — every item must sit in one gate. | E4: CDM Principal Designer / Meridian | F4: Yes
A5: Include in Pack? | B5: Set Yes / No / TBC once applicability is confirmed. | C5: Do not leave items at TBC once scope is fixed. | E5: Client | F5: No
A6: Status | B6: Not Started / In Progress / Complete against actual issue status. | C6: Do not mark Complete before formal issue/acceptance. | E6: Client / CDM Principal Designer | F6: TBC
A7: Priority | B7: Critical / High / Medium by delivery risk. Left blank deliberately — source register carried no priority. | C7: Do not invent criticality; base it on programme need-by dates. | E7: Client / Meridian | F7: Not Started
A8: Owner / Lead Party | B8: Verbatim from source. Note Stage 1 mixes Meridian submissions and client tender info. | C8: Do not silently re-assign a Client/designer deliverable to Meridian. | E8: Client / design team | F8: In Progress
A9: Due Date | B9: Link to the design programme / information release need-by date. | C9: Do not use arbitrary dates disconnected from programme. | E9: Client initially / Meridian post-appointment | F9: Complete
A10: TYPE / File Name | B10: Proposed PROJ-DDR-[TYPE]-[####]. Confirm before adopting. | C10: Do not overwrite the design Ref (0.01-4.21). | E10: MEP / specialist designers | F10: Critical
E11: MEP Designer | F11: High
E12: Meridian | F12: Medium
E13: Meridian / CDP specialists
E14: Meridian / Client
E15: Meridian / appointed architectural designer
E16: Meridian / relevant designers
E17: Relevant designers
E18: Relevant designers / CDP specialists
E19: Relevant engineers
